{
  "ticker": "TCS",
  "underlying_price": 3920.0,
  "iv_history": [18.0, 19.2, 17.5, 20.8, 22.0, 19.8, 18.3, 17.0, 16.5, 19.2, 20.8, 22.5, 24.0, 25.5, 23.8, 21.9, 20.0, 18.8, 17.5, 20.2, 21.8, 23.5, 25.2, 27.0, 26.1, 24.0, 22.3, 20.5, 19.6, 18.5, 17.0, 19.5, 21.0, 22.5, 24.5, 26.2, 25.0, 23.1, 21.0, 19.5, 18.2, 17.2, 19.8, 21.5, 23.2, 24.8, 23.5, 21.8, 20.0, 18.5, 17.2, 20.0],
  "expirations": [
    {
      "date": "2025-02-27",
      "chain": [
        {"strike": 3800, "call": {"bid": 138, "ask": 142, "last": 140, "volume": 2800, "oi": 15000, "iv": 0.21}, "put": {"bid": 18, "ask": 22, "last": 20, "volume": 1500, "oi": 9000, "iv": 0.19}},
        {"strike": 3840, "call": {"bid": 108, "ask": 112, "last": 110, "volume": 3200, "oi": 18000, "iv": 0.205}, "put": {"bid": 28, "ask": 32, "last": 30, "volume": 2000, "oi": 11000, "iv": 0.195}},
        {"strike": 3880, "call": {"bid": 72, "ask": 76, "last": 74, "volume": 4000, "oi": 22000, "iv": 0.20}, "put": {"bid": 34, "ask": 38, "last": 36, "volume": 2800, "oi": 14000, "iv": 0.20}},
        {"strike": 3920, "call": {"bid": 48, "ask": 52, "last": 50, "volume": 5500, "oi": 28000, "iv": 0.195}, "put": {"bid": 50, "ask": 54, "last": 52, "volume": 5000, "oi": 25000, "iv": 0.195}},
        {"strike": 3960, "call": {"bid": 30, "ask": 34, "last": 32, "volume": 4200, "oi": 20000, "iv": 0.20}, "put": {"bid": 72, "ask": 76, "last": 74, "volume": 3500, "oi": 18000, "iv": 0.205}},
        {"strike": 4000, "call": {"bid": 18, "ask": 22, "last": 20, "volume": 3000, "oi": 16000, "iv": 0.21}, "put": {"bid": 100, "ask": 105, "last": 102, "volume": 2500, "oi": 14000, "iv": 0.215}}
      ]
    },
    {
      "date": "2025-03-27",
      "chain": [
        {"strike": 3800, "call": {"bid": 175, "ask": 182, "last": 178, "volume": 1800, "oi": 10000, "iv": 0.225}, "put": {"bid": 52, "ask": 58, "last": 55, "volume": 1200, "oi": 7000, "iv": 0.22}},
        {"strike": 3880, "call": {"bid": 115, "ask": 122, "last": 118, "volume": 2200, "oi": 13000, "iv": 0.22}, "put": {"bid": 75, "ask": 82, "last": 78, "volume": 1800, "oi": 9500, "iv": 0.225}},
        {"strike": 3920, "call": {"bid": 90, "ask": 97, "last": 93, "volume": 2800, "oi": 15000, "iv": 0.215}, "put": {"bid": 92, "ask": 99, "last": 95, "volume": 2500, "oi": 14000, "iv": 0.215}},
        {"strike": 3960, "call": {"bid": 68, "ask": 75, "last": 71, "volume": 2000, "oi": 12000, "iv": 0.22}, "put": {"bid": 110, "ask": 118, "last": 114, "volume": 1600, "oi": 10000, "iv": 0.225}},
        {"strike": 4000, "call": {"bid": 48, "ask": 55, "last": 51, "volume": 1500, "oi": 9000, "iv": 0.225}, "put": {"bid": 130, "ask": 138, "last": 134, "volume": 1200, "oi": 8000, "iv": 0.23}},
        {"strike": 4080, "call": {"bid": 22, "ask": 28, "last": 25, "volume": 1000, "oi": 6000, "iv": 0.235}, "put": {"bid": 185, "ask": 195, "last": 190, "volume": 800, "oi": 5000, "iv": 0.24}}
      ]
    }
  ]
}
